odoo/addons/purchase_order_line_description/README.rst
odoo/addons/purchase_order_line_description/__init__.py
odoo/addons/purchase_order_line_description/__manifest__.py
odoo/addons/purchase_order_line_description/i18n/de.po
odoo/addons/purchase_order_line_description/i18n/es.po
odoo/addons/purchase_order_line_description/i18n/es_MX.po
odoo/addons/purchase_order_line_description/i18n/fi.po
odoo/addons/purchase_order_line_description/i18n/fr.po
odoo/addons/purchase_order_line_description/i18n/it.po
odoo/addons/purchase_order_line_description/i18n/nl_NL.po
odoo/addons/purchase_order_line_description/i18n/pt_BR.po
odoo/addons/purchase_order_line_description/i18n/pt_PT.po
odoo/addons/purchase_order_line_description/i18n/purchase_order_line_description.pot
odoo/addons/purchase_order_line_description/i18n/ro.po
odoo/addons/purchase_order_line_description/i18n/sl.po
odoo/addons/purchase_order_line_description/models/__init__.py
odoo/addons/purchase_order_line_description/models/purchase_order_line.py
odoo/addons/purchase_order_line_description/models/res_config_settings.py
odoo/addons/purchase_order_line_description/readme/CONFIGURE.rst
odoo/addons/purchase_order_line_description/readme/CONTRIBUTORS.rst
odoo/addons/purchase_order_line_description/readme/DESCRIPTION.rst
odoo/addons/purchase_order_line_description/readme/USAGE.rst
odoo/addons/purchase_order_line_description/security/res_groups_security.xml
odoo/addons/purchase_order_line_description/static/description/icon.png
odoo/addons/purchase_order_line_description/static/description/index.html
odoo/addons/purchase_order_line_description/tests/__init__.py
odoo/addons/purchase_order_line_description/tests/test_purchase_order_line_description.py
odoo/addons/purchase_order_line_description/views/purchase_config_settings_view.xml
odoo12_addon_purchase_order_line_description-12.0.1.0.1.dist-info/METADATA
odoo12_addon_purchase_order_line_description-12.0.1.0.1.dist-info/WHEEL
odoo12_addon_purchase_order_line_description-12.0.1.0.1.dist-info/top_level.txt
odoo12_addon_purchase_order_line_description-12.0.1.0.1.dist-info/RECORD
