Metadata-Version: 2.1
Name: odoo12-addon-purchase-order-line-description
Version: 12.0.1.0.1
Summary: Purchase order line description
Home-page: https://github.com/OCA/purchase-workflow
Author: Agile Business Group, Odoo Community Association (OCA)
Author-email: support@odoo-community.org
License: AGPL-3
Platform: UNKNOWN
Classifier: Programming Language :: Python
Classifier: Framework :: Odoo
Classifier: License :: OSI Approved :: GNU Affero General Public License v3
Requires-Python: >=3.5
Requires-Dist: odoo (<12.1dev,>=12.0a)
